AUTHORS
LICENSE
MANIFEST.in
README.md
setup.py
thunderdome_flask/VERSION
thunderdome_flask/__init__.py
thunderdome_flask/converters.py
thunderdome_flask/register.py
thunderdome_flask.egg-info/PKG-INFO
thunderdome_flask.egg-info/SOURCES.txt
thunderdome_flask.egg-info/dependency_links.txt
thunderdome_flask.egg-info/top_level.txt