Metadata-Version: 1.0
Name: thunderdome-flask
Version: 1.0.2
Summary: Thunderdome Flask integration
Home-page: https://github.com/StartTheShift/thunderdome-flask
Author: etscrivner
Author-email: zenogais@gmail.com
License: BSD
Keywords: cassandra,titan,ogm,thunderdome
Platform: UNKNOWN
Classifier: Development Status :: 3 - Alpha
Classifier: Environment :: Web Environment
Classifier: Environment :: Plugins
Classifier: License :: OSI Approved :: BSD License
Classifier: Operating System :: OS Independent
Classifier: Programming Language :: Python :: 2.6
Classifier: Programming Language :: Python :: 2.7
Classifier: Topic :: Internet :: WWW/HTTP
Classifier: Topic :: Software Development :: Libraries :: Python Modules
